Workbook

Sheet README
A1: VENDOR ELIGIBILITY, PERFORMANCE EVALUATION
A2: & EXECUTIVE DASHBOARD SYSTEM
A4: Project Overview
A5: This workbook provides a comprehensive, enterprise-grade vendor evaluation framework designed for procurement teams.
A6: It automates the end-to-end assessment of potential vendors through structured eligibility screening, weighted technical scoring,
A7: normalized financial evaluation, and composite ranking — supporting data-driven, defensible procurement decisions.
A9: Business Problem
A10: Organizations face subjective, inconsistent, and manual vendor selection processes. This leads to suboptimal partnerships,
A11: compliance risk exposure, budget overruns, and an inability to benchmark vendor performance across categories and regions.
A13: Methodology
A14: 1. Raw Data Ingestion — 120 vendor profiles with company details, industry, region, and bid pricing.
A15: 2. Eligibility Screening — 8 mandatory pass/fail criteria (min. 3 yrs business, 50+ employees, $1M+ revenue, valid contact, active region, bid cap, tech readiness, financial health).
... A33: and a score distribution chart. Use Slicers on the Pivot Tables for interactive filtering by Industry, Region, and Status.

Sheet Raw_Data
A1: Company Name | B1: Industry | C1: Region | D1: Years in Business | E1: Employees | F1: Annual Revenue ($) | G1: Contact Info | H1: Bid Price ($)
A2: Nexus Solutions Omega | B2: Manufacturing | C2: Europe | D2: 6 | E2: 889 | F2: 365300269 | G2: contact@nexussolutionsomega.com | H2: 1653292
A3: Apex Solutions Beta | B3: Manufacturing | C3: Europe | D3: 18 | E3: 4981 | F3: 16246390 | G3: contact@apexsolutionsbeta.com | H3: 1277016
A4: Cobalt Corp Nova | B4: Retail | C4: North America | D4: 7 | E4: 3512 | F4: 184670606 | G4: contact@cobaltcorpnova.com | H4: 682738
A5: Prime Partners Beta | B5: Energy | C5: Asia Pacific | D5: 21 | E5: 2216 | F5: 435323695 | G5: contact@primepartnersbeta.com | H5: 191122
A6: Prime Dynamics Omega | B6: Energy | C6: Middle East & Africa | D6: 8 | E6: 619 | F6: 26601779 | G6: contact@primedynamicsomega.com | H6: 1486769
A7: Nexus Partners Omega | B7: Logistics | C7: Asia Pacific | D7: 7 | E7: 3082 | F7: 192734506 | G7: contact@nexuspartnersomega.com | H7: 539368
A8: Orion Group Pro | B8: Manufacturing | C8: Europe | D8: 16 | E8: 3158 | F8: 146927134 | G8: contact@oriongrouppro.com | H8: 1442176
A9: Zenith Solutions Prime | B9: Telecom | C9: Asia Pacific | D9: 4 | E9: 1778 | F9: 492236220 | G9: contact@zenithsolutionsprime.com | H9: 1289462
A10: Atlas Industries Gamma | B10: Retail | C10: Europe | D10: 9 | E10: 4648 | F10: 291361229 | G10: contact@atlasindustriesgamma.com | H10: 651009
A11: Sterling Corp Gamma | B11: Logistics | C11: North America | D11: 3 | E11: 948 | F11: 84056059 | G11: contact@sterlingcorpgamma.com | H11: 1415849
A12: Prime Partners Core | B12: Logistics | C12: Middle East & Africa | D12: 10 | E12: 4582 | F12: 464127581 | G12: contact@primepartnerscore.com | H12: 124077
A13: Meridian Systems Omega | B13: Telecom | C13: Europe | D13: 16 | E13: 76 | F13: 389670222 | G13: contact@meridiansystemsomega.com | H13: 1936796
... A121: Prime Partners Alpha | B121: Telecom | C121: North America | D121: 16 | E121: 687 | F121: 464841790 | G121: contact@primepartnersalpha.com | H121: 756535

Sheet Eligibility_Check
A1: Company Name | B1: Industry | C1: Region | D1: C1: Min 3 Yrs | E1: C2: Min 50 Emp | F1: C3: Min $1M Rev | G1: C4: Valid Contact | H1: C5: Active Region | I1: C6: Bid Under $1.5M | J1: C7: Tech Ready | K1: C8: Fin Healthy | L1: Final Status
A2: =Raw_Data!A2 | B2: =Raw_Data!B2 | C2: =Raw_Data!C2 | D2: =IF(Raw_Data!D2>=3,"PASS","FAIL") | E2: =IF(Raw_Data!E2>=50,"PASS","FAIL") | F2: =IF(Raw_Data!F2>=1000000,"PASS","FAIL") | G2: =IF(ISNUMBER(SEARCH("@",Raw_Data!G2)),"PASS","FAIL") | H2: =IF(OR(Raw_Data!C2="North America",Raw_Data!C2="Europe",Raw_Data!C2="Asia Pacific"),"PASS","FAIL") | I2: =IF(Raw_Data!H2<=1500000,"PASS","FAIL") | J2: =IF(Raw_Data!D2>=5,"PASS","FAIL") | K2: =IF(Raw_Data!F2>=5000000,"PASS","FAIL") | L2: =IF(AND(D2="PASS",E2="PASS",F2="PASS",G2="PASS",H2="PASS",I2="PASS",J2="PASS",K2="PASS"),"Qualified","Disqualified")
A3: =Raw_Data!A3 | B3: =Raw_Data!B3 | C3: =Raw_Data!C3 | D3: =IF(Raw_Data!D3>=3,"PASS","FAIL") | E3: =IF(Raw_Data!E3>=50,"PASS","FAIL") | F3: =IF(Raw_Data!F3>=1000000,"PASS","FAIL") | G3: =IF(ISNUMBER(SEARCH("@",Raw_Data!G3)),"PASS","FAIL") | H3: =IF(OR(Raw_Data!C3="North America",Raw_Data!C3="Europe",Raw_Data!C3="Asia Pacific"),"PASS","FAIL") | I3: =IF(Raw_Data!H3<=1500000,"PASS","FAIL") | J3: =IF(Raw_Data!D3>=5,"PASS","FAIL") | K3: =IF(Raw_Data!F3>=5000000,"PASS","FAIL") | L3: =IF(AND(D3="PASS",E3="PASS",F3="PASS",G3="PASS",H3="PASS",I3="PASS",J3="PASS",K3="PASS"),"Qualified","Disqualified")
A4: =Raw_Data!A4 | B4: =Raw_Data!B4 | C4: =Raw_Data!C4 | D4: =IF(Raw_Data!D4>=3,"PASS","FAIL") | E4: =IF(Raw_Data!E4>=50,"PASS","FAIL") | F4: =IF(Raw_Data!F4>=1000000,"PASS","FAIL") | G4: =IF(ISNUMBER(SEARCH("@",Raw_Data!G4)),"PASS","FAIL") | H4: =IF(OR(Raw_Data!C4="North America",Raw_Data!C4="Europe",Raw_Data!C4="Asia Pacific"),"PASS","FAIL") | I4: =IF(Raw_Data!H4<=1500000,"PASS","FAIL") | J4: =IF(Raw_Data!D4>=5,"PASS","FAIL") | K4: =IF(Raw_Data!F4>=5000000,"PASS","FAIL") | L4: =IF(AND(D4="PASS",E4="PASS",F4="PASS",G4="PASS",H4="PASS",I4="PASS",J4="PASS",K4="PASS"),"Qualified","Disqualified")
A5: =Raw_Data!A5 | B5: =Raw_Data!B5 | C5: =Raw_Data!C5 | D5: =IF(Raw_Data!D5>=3,"PASS","FAIL") | E5: =IF(Raw_Data!E5>=50,"PASS","FAIL") | F5: =IF(Raw_Data!F5>=1000000,"PASS","FAIL") | G5: =IF(ISNUMBER(SEARCH("@",Raw_Data!G5)),"PASS","FAIL") | H5: =IF(OR(Raw_Data!C5="North America",Raw_Data!C5="Europe",Raw_Data!C5="Asia Pacific"),"PASS","FAIL") | I5: =IF(Raw_Data!H5<=1500000,"PASS","FAIL") | J5: =IF(Raw_Data!D5>=5,"PASS","FAIL") | K5: =IF(Raw_Data!F5>=5000000,"PASS","FAIL") | L5: =IF(AND(D5="PASS",E5="PASS",F5="PASS",G5="PASS",H5="PASS",I5="PASS",J5="PASS",K5="PASS"),"Qualified","Disqualified")
A6: =Raw_Data!A6 | B6: =Raw_Data!B6 | C6: =Raw_Data!C6 | D6: =IF(Raw_Data!D6>=3,"PASS","FAIL") | E6: =IF(Raw_Data!E6>=50,"PASS","FAIL") | F6: =IF(Raw_Data!F6>=1000000,"PASS","FAIL") | G6: =IF(ISNUMBER(SEARCH("@",Raw_Data!G6)),"PASS","FAIL") | H6: =IF(OR(Raw_Data!C6="North America",Raw_Data!C6="Europe",Raw_Data!C6="Asia Pacific"),"PASS","FAIL") | I6: =IF(Raw_Data!H6<=1500000,"PASS","FAIL") | J6: =IF(Raw_Data!D6>=5,"PASS","FAIL") | K6: =IF(Raw_Data!F6>=5000000,"PASS","FAIL") | L6: =IF(AND(D6="PASS",E6="PASS",F6="PASS",G6="PASS",H6="PASS",I6="PASS",J6="PASS",K6="PASS"),"Qualified","Disqualified")
A7: =Raw_Data!A7 | B7: =Raw_Data!B7 | C7: =Raw_Data!C7 | D7: =IF(Raw_Data!D7>=3,"PASS","FAIL") | E7: =IF(Raw_Data!E7>=50,"PASS","FAIL") | F7: =IF(Raw_Data!F7>=1000000,"PASS","FAIL") | G7: =IF(ISNUMBER(SEARCH("@",Raw_Data!G7)),"PASS","FAIL") | H7: =IF(OR(Raw_Data!C7="North America",Raw_Data!C7="Europe",Raw_Data!C7="Asia Pacific"),"PASS","FAIL") | I7: =IF(Raw_Data!H7<=1500000,"PASS","FAIL") | J7: =IF(Raw_Data!D7>=5,"PASS","FAIL") | K7: =IF(Raw_Data!F7>=5000000,"PASS","FAIL") | L7: =IF(AND(D7="PASS",E7="PASS",F7="PASS",G7="PASS",H7="PASS",I7="PASS",J7="PASS",K7="PASS"),"Qualified","Disqualified")
A8: =Raw_Data!A8 | B8: =Raw_Data!B8 | C8: =Raw_Data!C8 | D8: =IF(Raw_Data!D8>=3,"PASS","FAIL") | E8: =IF(Raw_Data!E8>=50,"PASS","FAIL") | F8: =IF(Raw_Data!F8>=1000000,"PASS","FAIL") | G8: =IF(ISNUMBER(SEARCH("@",Raw_Data!G8)),"PASS","FAIL") | H8: =IF(OR(Raw_Data!C8="North America",Raw_Data!C8="Europe",Raw_Data!C8="Asia Pacific"),"PASS","FAIL") | I8: =IF(Raw_Data!H8<=1500000,"PASS","FAIL") | J8: =IF(Raw_Data!D8>=5,"PASS","FAIL") | K8: =IF(Raw_Data!F8>=5000000,"PASS","FAIL") | L8: =IF(AND(D8="PASS",E8="PASS",F8="PASS",G8="PASS",H8="PASS",I8="PASS",J8="PASS",K8="PASS"),"Qualified","Disqualified")
A9: =Raw_Data!A9 | B9: =Raw_Data!B9 | C9: =Raw_Data!C9 | D9: =IF(Raw_Data!D9>=3,"PASS","FAIL") | E9: =IF(Raw_Data!E9>=50,"PASS","FAIL") | F9: =IF(Raw_Data!F9>=1000000,"PASS","FAIL") | G9: =IF(ISNUMBER(SEARCH("@",Raw_Data!G9)),"PASS","FAIL") | H9: =IF(OR(Raw_Data!C9="North America",Raw_Data!C9="Europe",Raw_Data!C9="Asia Pacific"),"PASS","FAIL") | I9: =IF(Raw_Data!H9<=1500000,"PASS","FAIL") | J9: =IF(Raw_Data!D9>=5,"PASS","FAIL") | K9: =IF(Raw_Data!F9>=5000000,"PASS","FAIL") | L9: =IF(AND(D9="PASS",E9="PASS",F9="PASS",G9="PASS",H9="PASS",I9="PASS",J9="PASS",K9="PASS"),"Qualified","Disqualified")
A10: =Raw_Data!A10 | B10: =Raw_Data!B10 | C10: =Raw_Data!C10 | D10: =IF(Raw_Data!D10>=3,"PASS","FAIL") | E10: =IF(Raw_Data!E10>=50,"PASS","FAIL") | F10: =IF(Raw_Data!F10>=1000000,"PASS","FAIL") | G10: =IF(ISNUMBER(SEARCH("@",Raw_Data!G10)),"PASS","FAIL") | H10: =IF(OR(Raw_Data!C10="North America",Raw_Data!C10="Europe",Raw_Data!C10="Asia Pacific"),"PASS","FAIL") | I10: =IF(Raw_Data!H10<=1500000,"PASS","FAIL") | J10: =IF(Raw_Data!D10>=5,"PASS","FAIL") | K10: =IF(Raw_Data!F10>=5000000,"PASS","FAIL") | L10: =IF(AND(D10="PASS",E10="PASS",F10="PASS",G10="PASS",H10="PASS",I10="PASS",J10="PASS",K10="PASS"),"Qualified","Disqualified")
A11: =Raw_Data!A11 | B11: =Raw_Data!B11 | C11: =Raw_Data!C11 | D11: =IF(Raw_Data!D11>=3,"PASS","FAIL") | E11: =IF(Raw_Data!E11>=50,"PASS","FAIL") | F11: =IF(Raw_Data!F11>=1000000,"PASS","FAIL") | G11: =IF(ISNUMBER(SEARCH("@",Raw_Data!G11)),"PASS","FAIL") | H11: =IF(OR(Raw_Data!C11="North America",Raw_Data!C11="Europe",Raw_Data!C11="Asia Pacific"),"PASS","FAIL") | I11: =IF(Raw_Data!H11<=1500000,"PASS","FAIL") | J11: =IF(Raw_Data!D11>=5,"PASS","FAIL") | K11: =IF(Raw_Data!F11>=5000000,"PASS","FAIL") | L11: =IF(AND(D11="PASS",E11="PASS",F11="PASS",G11="PASS",H11="PASS",I11="PASS",J11="PASS",K11="PASS"),"Qualified","Disqualified")
A12: =Raw_Data!A12 | B12: =Raw_Data!B12 | C12: =Raw_Data!C12 | D12: =IF(Raw_Data!D12>=3,"PASS","FAIL") | E12: =IF(Raw_Data!E12>=50,"PASS","FAIL") | F12: =IF(Raw_Data!F12>=1000000,"PASS","FAIL") | G12: =IF(ISNUMBER(SEARCH("@",Raw_Data!G12)),"PASS","FAIL") | H12: =IF(OR(Raw_Data!C12="North America",Raw_Data!C12="Europe",Raw_Data!C12="Asia Pacific"),"PASS","FAIL") | I12: =IF(Raw_Data!H12<=1500000,"PASS","FAIL") | J12: =IF(Raw_Data!D12>=5,"PASS","FAIL") | K12: =IF(Raw_Data!F12>=5000000,"PASS","FAIL") | L12: =IF(AND(D12="PASS",E12="PASS",F12="PASS",G12="PASS",H12="PASS",I12="PASS",J12="PASS",K12="PASS"),"Qualified","Disqualified")
A13: =Raw_Data!A13 | B13: =Raw_Data!B13 | C13: =Raw_Data!C13 | D13: =IF(Raw_Data!D13>=3,"PASS","FAIL") | E13: =IF(Raw_Data!E13>=50,"PASS","FAIL") | F13: =IF(Raw_Data!F13>=1000000,"PASS","FAIL") | G13: =IF(ISNUMBER(SEARCH("@",Raw_Data!G13)),"PASS","FAIL") | H13: =IF(OR(Raw_Data!C13="North America",Raw_Data!C13="Europe",Raw_Data!C13="Asia Pacific"),"PASS","FAIL") | I13: =IF(Raw_Data!H13<=1500000,"PASS","FAIL") | J13: =IF(Raw_Data!D13>=5,"PASS","FAIL") | K13: =IF(Raw_Data!F13>=5000000,"PASS","FAIL") | L13: =IF(AND(D13="PASS",E13="PASS",F13="PASS",G13="PASS",H13="PASS",I13="PASS",J13="PASS",K13="PASS"),"Qualified","Disqualified")
... A121: =Raw_Data!A121 | B121: =Raw_Data!B121 | C121: =Raw_Data!C121 | D121: =IF(Raw_Data!D121>=3,"PASS","FAIL") | E121: =IF(Raw_Data!E121>=50,"PASS","FAIL") | F121: =IF(Raw_Data!F121>=1000000,"PASS","FAIL") | G121: =IF(ISNUMBER(SEARCH("@",Raw_Data!G121)),"PASS","FAIL") | H121: =IF(OR(Raw_Data!C121="North America",Raw_Data!C121="Europe",Raw_Data!C121="Asia Pacific"),"PASS","FAIL") | I121: =IF(Raw_Data!H121<=1500000,"PASS","FAIL") | J121: =IF(Raw_Data!D121>=5,"PASS","FAIL") | K121: =IF(Raw_Data!F121>=5000000,"PASS","FAIL") | L121: =IF(AND(D121="PASS",E121="PASS",F121="PASS",G121="PASS",H121="PASS",I121="PASS",J121="PASS",K121="PASS"),"Qualified","Disqualified")

Sheet Technical_Scoring
A1: Company Name | B1: Industry | C1: Region | D1: Experience (25%) | E1: Team Strength (25%) | F1: Delivery (25%) | G1: Quality (25%) | H1: Weighted Total
A2: =Raw_Data!A2 | B2: =Raw_Data!B2 | C2: =Raw_Data!C2 | D2: 94 | E2: 60 | F2: 95 | G2: 87 | H2: =ROUND(D2*0.25+E2*0.25+F2*0.25+G2*0.25,1)
A3: =Raw_Data!A3 | B3: =Raw_Data!B3 | C3: =Raw_Data!C3 | D3: 72 | E3: 100 | F3: 99 | G3: 94 | H3: =ROUND(D3*0.25+E3*0.25+F3*0.25+G3*0.25,1)
A4: =Raw_Data!A4 | B4: =Raw_Data!B4 | C4: =Raw_Data!C4 | D4: 69 | E4: 68 | F4: 79 | G4: 66 | H4: =ROUND(D4*0.25+E4*0.25+F4*0.25+G4*0.25,1)
A5: =Raw_Data!A5 | B5: =Raw_Data!B5 | C5: =Raw_Data!C5 | D5: 89 | E5: 89 | F5: 65 | G5: 84 | H5: =ROUND(D5*0.25+E5*0.25+F5*0.25+G5*0.25,1)
A6: =Raw_Data!A6 | B6: =Raw_Data!B6 | C6: =Raw_Data!C6 | D6: 74 | E6: 73 | F6: 63 | G6: 74 | H6: =ROUND(D6*0.25+E6*0.25+F6*0.25+G6*0.25,1)
A7: =Raw_Data!A7 | B7: =Raw_Data!B7 | C7: =Raw_Data!C7 | D7: 77 | E7: 99 | F7: 99 | G7: 64 | H7: =ROUND(D7*0.25+E7*0.25+F7*0.25+G7*0.25,1)
A8: =Raw_Data!A8 | B8: =Raw_Data!B8 | C8: =Raw_Data!C8 | D8: 95 | E8: 69 | F8: 78 | G8: 63 | H8: =ROUND(D8*0.25+E8*0.25+F8*0.25+G8*0.25,1)
A9: =Raw_Data!A9 | B9: =Raw_Data!B9 | C9: =Raw_Data!C9 | D9: 80 | E9: 68 | F9: 99 | G9: 91 | H9: =ROUND(D9*0.25+E9*0.25+F9*0.25+G9*0.25,1)
A10: =Raw_Data!A10 | B10: =Raw_Data!B10 | C10: =Raw_Data!C10 | D10: 97 | E10: 82 | F10: 95 | G10: 85 | H10: =ROUND(D10*0.25+E10*0.25+F10*0.25+G10*0.25,1)
A11: =Raw_Data!A11 | B11: =Raw_Data!B11 | C11: =Raw_Data!C11 | D11: 70 | E11: 98 | F11: 85 | G11: 98 | H11: =ROUND(D11*0.25+E11*0.25+F11*0.25+G11*0.25,1)
A12: =Raw_Data!A12 | B12: =Raw_Data!B12 | C12: =Raw_Data!C12 | D12: 67 | E12: 98 | F12: 92 | G12: 77 | H12: =ROUND(D12*0.25+E12*0.25+F12*0.25+G12*0.25,1)
A13: =Raw_Data!A13 | B13: =Raw_Data!B13 | C13: =Raw_Data!C13 | D13: 76 | E13: 87 | F13: 69 | G13: 92 | H13: =ROUND(D13*0.25+E13*0.25+F13*0.25+G13*0.25,1)
... A121: =Raw_Data!A121 | B121: =Raw_Data!B121 | C121: =Raw_Data!C121 | D121: 96 | E121: 82 | F121: 94 | G121: 85 | H121: =ROUND(D121*0.25+E121*0.25+F121*0.25+G121*0.25,1)

Sheet Financial_Evaluation
A1: Company Name | B1: Bid Price ($) | C1: Lowest Bid ($) | D1: Normalized Financial Score | I1: Lowest Bid (ref)
A2: =Raw_Data!A2 | B2: =Raw_Data!H2 | C2: =$I$2 | D2: =IF(B2=0,0,ROUND(($I$2/B2)*100,1)) | I2: =MIN(Raw_Data!$H$2:$H$121)
A3: =Raw_Data!A3 | B3: =Raw_Data!H3 | C3: =$I$2 | D3: =IF(B3=0,0,ROUND(($I$2/B3)*100,1))
A4: =Raw_Data!A4 | B4: =Raw_Data!H4 | C4: =$I$2 | D4: =IF(B4=0,0,ROUND(($I$2/B4)*100,1))
A5: =Raw_Data!A5 | B5: =Raw_Data!H5 | C5: =$I$2 | D5: =IF(B5=0,0,ROUND(($I$2/B5)*100,1))
A6: =Raw_Data!A6 | B6: =Raw_Data!H6 | C6: =$I$2 | D6: =IF(B6=0,0,ROUND(($I$2/B6)*100,1))
A7: =Raw_Data!A7 | B7: =Raw_Data!H7 | C7: =$I$2 | D7: =IF(B7=0,0,ROUND(($I$2/B7)*100,1))
A8: =Raw_Data!A8 | B8: =Raw_Data!H8 | C8: =$I$2 | D8: =IF(B8=0,0,ROUND(($I$2/B8)*100,1))
A9: =Raw_Data!A9 | B9: =Raw_Data!H9 | C9: =$I$2 | D9: =IF(B9=0,0,ROUND(($I$2/B9)*100,1))
A10: =Raw_Data!A10 | B10: =Raw_Data!H10 | C10: =$I$2 | D10: =IF(B10=0,0,ROUND(($I$2/B10)*100,1))
A11: =Raw_Data!A11 | B11: =Raw_Data!H11 | C11: =$I$2 | D11: =IF(B11=0,0,ROUND(($I$2/B11)*100,1))
A12: =Raw_Data!A12 | B12: =Raw_Data!H12 | C12: =$I$2 | D12: =IF(B12=0,0,ROUND(($I$2/B12)*100,1))
A13: =Raw_Data!A13 | B13: =Raw_Data!H13 | C13: =$I$2 | D13: =IF(B13=0,0,ROUND(($I$2/B13)*100,1))
A14: =Raw_Data!A14 | B14: =Raw_Data!H14 | C14: =$I$2 | D14: =IF(B14=0,0,ROUND(($I$2/B14)*100,1))
... A121: =Raw_Data!A121 | B121: =Raw_Data!H121 | C121: =$I$2 | D121: =IF(B121=0,0,ROUND(($I$2/B121)*100,1))

Sheet Final_Ranking
A1: Rank | B1: Company Name | C1: Industry | D1: Region | E1: Tech Score (70%) | F1: Fin Score (30%) | G1: Composite Score | H1: Eligibility Status
A2: =RANK.EQ(G2,$G$2:$G$121,0) | B2: =Raw_Data!A2 | C2: =Raw_Data!B2 | D2: =Raw_Data!C2 | E2: =ROUND(Technical_Scoring!H2*0.7,1) | F2: =ROUND(Financial_Evaluation!D2*0.3,1) | G2: =ROUND(E2+F2,1) | H2: =Eligibility_Check!L2
A3: =RANK.EQ(G3,$G$2:$G$121,0) | B3: =Raw_Data!A3 | C3: =Raw_Data!B3 | D3: =Raw_Data!C3 | E3: =ROUND(Technical_Scoring!H3*0.7,1) | F3: =ROUND(Financial_Evaluation!D3*0.3,1) | G3: =ROUND(E3+F3,1) | H3: =Eligibility_Check!L3
A4: =RANK.EQ(G4,$G$2:$G$121,0) | B4: =Raw_Data!A4 | C4: =Raw_Data!B4 | D4: =Raw_Data!C4 | E4: =ROUND(Technical_Scoring!H4*0.7,1) | F4: =ROUND(Financial_Evaluation!D4*0.3,1) | G4: =ROUND(E4+F4,1) | H4: =Eligibility_Check!L4
A5: =RANK.EQ(G5,$G$2:$G$121,0) | B5: =Raw_Data!A5 | C5: =Raw_Data!B5 | D5: =Raw_Data!C5 | E5: =ROUND(Technical_Scoring!H5*0.7,1) | F5: =ROUND(Financial_Evaluation!D5*0.3,1) | G5: =ROUND(E5+F5,1) | H5: =Eligibility_Check!L5
A6: =RANK.EQ(G6,$G$2:$G$121,0) | B6: =Raw_Data!A6 | C6: =Raw_Data!B6 | D6: =Raw_Data!C6 | E6: =ROUND(Technical_Scoring!H6*0.7,1) | F6: =ROUND(Financial_Evaluation!D6*0.3,1) | G6: =ROUND(E6+F6,1) | H6: =Eligibility_Check!L6
A7: =RANK.EQ(G7,$G$2:$G$121,0) | B7: =Raw_Data!A7 | C7: =Raw_Data!B7 | D7: =Raw_Data!C7 | E7: =ROUND(Technical_Scoring!H7*0.7,1) | F7: =ROUND(Financial_Evaluation!D7*0.3,1) | G7: =ROUND(E7+F7,1) | H7: =Eligibility_Check!L7
A8: =RANK.EQ(G8,$G$2:$G$121,0) | B8: =Raw_Data!A8 | C8: =Raw_Data!B8 | D8: =Raw_Data!C8 | E8: =ROUND(Technical_Scoring!H8*0.7,1) | F8: =ROUND(Financial_Evaluation!D8*0.3,1) | G8: =ROUND(E8+F8,1) | H8: =Eligibility_Check!L8
A9: =RANK.EQ(G9,$G$2:$G$121,0) | B9: =Raw_Data!A9 | C9: =Raw_Data!B9 | D9: =Raw_Data!C9 | E9: =ROUND(Technical_Scoring!H9*0.7,1) | F9: =ROUND(Financial_Evaluation!D9*0.3,1) | G9: =ROUND(E9+F9,1) | H9: =Eligibility_Check!L9
A10: =RANK.EQ(G10,$G$2:$G$121,0) | B10: =Raw_Data!A10 | C10: =Raw_Data!B10 | D10: =Raw_Data!C10 | E10: =ROUND(Technical_Scoring!H10*0.7,1) | F10: =ROUND(Financial_Evaluation!D10*0.3,1) | G10: =ROUND(E10+F10,1) | H10: =Eligibility_Check!L10
A11: =RANK.EQ(G11,$G$2:$G$121,0) | B11: =Raw_Data!A11 | C11: =Raw_Data!B11 | D11: =Raw_Data!C11 | E11: =ROUND(Technical_Scoring!H11*0.7,1) | F11: =ROUND(Financial_Evaluation!D11*0.3,1) | G11: =ROUND(E11+F11,1) | H11: =Eligibility_Check!L11
A12: =RANK.EQ(G12,$G$2:$G$121,0) | B12: =Raw_Data!A12 | C12: =Raw_Data!B12 | D12: =Raw_Data!C12 | E12: =ROUND(Technical_Scoring!H12*0.7,1) | F12: =ROUND(Financial_Evaluation!D12*0.3,1) | G12: =ROUND(E12+F12,1) | H12: =Eligibility_Check!L12
A13: =RANK.EQ(G13,$G$2:$G$121,0) | B13: =Raw_Data!A13 | C13: =Raw_Data!B13 | D13: =Raw_Data!C13 | E13: =ROUND(Technical_Scoring!H13*0.7,1) | F13: =ROUND(Financial_Evaluation!D13*0.3,1) | G13: =ROUND(E13+F13,1) | H13: =Eligibility_Check!L13
... A121: =RANK.EQ(G121,$G$2:$G$121,0) | B121: =Raw_Data!A121 | C121: =Raw_Data!B121 | D121: =Raw_Data!C121 | E121: =ROUND(Technical_Scoring!H121*0.7,1) | F121: =ROUND(Financial_Evaluation!D121*0.3,1) | G121: =ROUND(E121+F121,1) | H121: =Eligibility_Check!L121

Sheet Dashboard
B1: VENDOR EVALUATION EXECUTIVE DASHBOARD
B2: Procurement Analytics & Vendor Performance Overview
B4: Total Vendors | F4: Qualified | J4: Disqualified | N4: Avg Composite Score | R4: Top Ranked Vendor
B5: =COUNTA(Raw_Data!$A$2:$A$121) | F5: =COUNTIF(Eligibility_Check!$L$2:$L$121,"Qualified") | J5: =COUNTIF(Eligibility_Check!$L$2:$L$121,"Disqualified") | N5: =ROUND(AVERAGE(Final_Ranking!$G$2:$G$121),1) | R5: =XLOOKUP(1,Final_Ranking!$A$2:$A$121,Final_Ranking!$B$2:$B$121,"N/A")
B8: Status | C8: Count | L8: Score Range | M8: Count
B9: Qualified | C9: =COUNTIF(Eligibility_Check!$L$2:$L$121,"Qualified") | L9: 90-100 | M9: =COUNTIFS(Final_Ranking!$G$2:$G$121,">=90",Final_Ranking!$G$2:$G$121,"<=100")
B10: Disqualified | C10: =COUNTIF(Eligibility_Check!$L$2:$L$121,"Disqualified") | L10: 80-89 | M10: =COUNTIFS(Final_Ranking!$G$2:$G$121,">=80",Final_Ranking!$G$2:$G$121,"<90")
L11: 70-79 | M11: =COUNTIFS(Final_Ranking!$G$2:$G$121,">=70",Final_Ranking!$G$2:$G$121,"<80")
L12: 60-69 | M12: =COUNTIFS(Final_Ranking!$G$2:$G$121,">=60",Final_Ranking!$G$2:$G$121,"<70")
L13: <60 | M13: =COUNTIF(Final_Ranking!$G$2:$G$121,"<60")
B27: Industry Breakdown
B28: Industry | C28: Total | D28: Qualified | E28: Avg Score
B29: Technology | C29: =COUNTIF(Raw_Data!$B$2:$B$121,"Technology") | D29: =COUNTIFS(Raw_Data!$B$2:$B$121,"Technology",Eligibility_Check!$L$2:$L$121,"Qualified") | E29: =IFERROR(ROUND(AVERAGEIFS(Final_Ranking!$G$2:$G$121,Final_Ranking!$C$2:$C$121,"Technology"),1),"")
B30: Healthcare | C30: =COUNTIF(Raw_Data!$B$2:$B$121,"Healthcare") | D30: =COUNTIFS(Raw_Data!$B$2:$B$121,"Healthcare",Eligibility_Check!$L$2:$L$121,"Qualified") | E30: =IFERROR(ROUND(AVERAGEIFS(Final_Ranking!$G$2:$G$121,Final_Ranking!$C$2:$C$121,"Healthcare"),1),"")
B31: Finance | C31: =COUNTIF(Raw_Data!$B$2:$B$121,"Finance") | D31: =COUNTIFS(Raw_Data!$B$2:$B$121,"Finance",Eligibility_Check!$L$2:$L$121,"Qualified") | E31: =IFERROR(ROUND(AVERAGEIFS(Final_Ranking!$G$2:$G$121,Final_Ranking!$C$2:$C$121,"Finance"),1),"")
B32: Manufacturing | C32: =COUNTIF(Raw_Data!$B$2:$B$121,"Manufacturing") | D32: =COUNTIFS(Raw_Data!$B$2:$B$121,"Manufacturing",Eligibility_Check!$L$2:$L$121,"Qualified") | E32: =IFERROR(ROUND(AVERAGEIFS(Final_Ranking!$G$2:$G$121,Final_Ranking!$C$2:$C$121,"Manufacturing"),1),"")
B33: Retail | C33: =COUNTIF(Raw_Data!$B$2:$B$121,"Retail") | D33: =COUNTIFS(Raw_Data!$B$2:$B$121,"Retail",Eligibility_Check!$L$2:$L$121,"Qualified") | E33: =IFERROR(ROUND(AVERAGEIFS(Final_Ranking!$G$2:$G$121,Final_Ranking!$C$2:$C$121,"Retail"),1),"")
B34: Energy | C34: =COUNTIF(Raw_Data!$B$2:$B$121,"Energy") | D34: =COUNTIFS(Raw_Data!$B$2:$B$121,"Energy",Eligibility_Check!$L$2:$L$121,"Qualified") | E34: =IFERROR(ROUND(AVERAGEIFS(Final_Ranking!$G$2:$G$121,Final_Ranking!$C$2:$C$121,"Energy"),1),"")
B35: Telecom | C35: =COUNTIF(Raw_Data!$B$2:$B$121,"Telecom") | D35: =COUNTIFS(Raw_Data!$B$2:$B$121,"Telecom",Eligibility_Check!$L$2:$L$121,"Qualified") | E35: =IFERROR(ROUND(AVERAGEIFS(Final_Ranking!$G$2:$G$121,Final_Ranking!$C$2:$C$121,"Telecom"),1),"")
B36: Logistics | C36: =COUNTIF(Raw_Data!$B$2:$B$121,"Logistics") | D36: =COUNTIFS(Raw_Data!$B$2:$B$121,"Logistics",Eligibility_Check!$L$2:$L$121,"Qualified") | E36: =IFERROR(ROUND(AVERAGEIFS(Final_Ranking!$G$2:$G$121,Final_Ranking!$C$2:$C$121,"Logistics"),1),"")
B55: INTERACTIVE SLICER SETUP
B56: 1. Select any cell in the Final_Ranking data table.
B57: 2. Go to Insert > PivotTable. Click OK to place it on a new worksheet.
B58: 3. Drag 'Industry', 'Region', and 'Eligibility Status' to the Filters area.
B59: 4. With the PivotTable selected, go to PivotTable Analyze > Insert Slicer.
B60: 5. Select 'Industry', 'Region', and 'Eligibility Status' to create slicers.
B61: 6. Right-click each slicer > Report Connections > connect to all PivotCharts.
B62: 7. Now use the slicers to filter all charts and KPI cards interactively.

Sheet Pivot_Support
A1: Company Name | B1: Industry | C1: Region | D1: Status | E1: Composite Score | F1: Rank | G1: Bid Price
A2: =Final_Ranking!B2 | B2: =Final_Ranking!C2 | C2: =Final_Ranking!D2 | D2: =Final_Ranking!H2 | E2: =Final_Ranking!G2 | F2: =Final_Ranking!A2 | G2: =Raw_Data!H2
A3: =Final_Ranking!B3 | B3: =Final_Ranking!C3 | C3: =Final_Ranking!D3 | D3: =Final_Ranking!H3 | E3: =Final_Ranking!G3 | F3: =Final_Ranking!A3 | G3: =Raw_Data!H3
A4: =Final_Ranking!B4 | B4: =Final_Ranking!C4 | C4: =Final_Ranking!D4 | D4: =Final_Ranking!H4 | E4: =Final_Ranking!G4 | F4: =Final_Ranking!A4 | G4: =Raw_Data!H4
A5: =Final_Ranking!B5 | B5: =Final_Ranking!C5 | C5: =Final_Ranking!D5 | D5: =Final_Ranking!H5 | E5: =Final_Ranking!G5 | F5: =Final_Ranking!A5 | G5: =Raw_Data!H5
A6: =Final_Ranking!B6 | B6: =Final_Ranking!C6 | C6: =Final_Ranking!D6 | D6: =Final_Ranking!H6 | E6: =Final_Ranking!G6 | F6: =Final_Ranking!A6 | G6: =Raw_Data!H6
A7: =Final_Ranking!B7 | B7: =Final_Ranking!C7 | C7: =Final_Ranking!D7 | D7: =Final_Ranking!H7 | E7: =Final_Ranking!G7 | F7: =Final_Ranking!A7 | G7: =Raw_Data!H7
A8: =Final_Ranking!B8 | B8: =Final_Ranking!C8 | C8: =Final_Ranking!D8 | D8: =Final_Ranking!H8 | E8: =Final_Ranking!G8 | F8: =Final_Ranking!A8 | G8: =Raw_Data!H8
A9: =Final_Ranking!B9 | B9: =Final_Ranking!C9 | C9: =Final_Ranking!D9 | D9: =Final_Ranking!H9 | E9: =Final_Ranking!G9 | F9: =Final_Ranking!A9 | G9: =Raw_Data!H9
A10: =Final_Ranking!B10 | B10: =Final_Ranking!C10 | C10: =Final_Ranking!D10 | D10: =Final_Ranking!H10 | E10: =Final_Ranking!G10 | F10: =Final_Ranking!A10 | G10: =Raw_Data!H10
A11: =Final_Ranking!B11 | B11: =Final_Ranking!C11 | C11: =Final_Ranking!D11 | D11: =Final_Ranking!H11 | E11: =Final_Ranking!G11 | F11: =Final_Ranking!A11 | G11: =Raw_Data!H11
A12: =Final_Ranking!B12 | B12: =Final_Ranking!C12 | C12: =Final_Ranking!D12 | D12: =Final_Ranking!H12 | E12: =Final_Ranking!G12 | F12: =Final_Ranking!A12 | G12: =Raw_Data!H12
A13: =Final_Ranking!B13 | B13: =Final_Ranking!C13 | C13: =Final_Ranking!D13 | D13: =Final_Ranking!H13 | E13: =Final_Ranking!G13 | F13: =Final_Ranking!A13 | G13: =Raw_Data!H13
... A121: =Final_Ranking!B121 | B121: =Final_Ranking!C121 | C121: =Final_Ranking!D121 | D121: =Final_Ranking!H121 | E121: =Final_Ranking!G121 | F121: =Final_Ranking!A121 | G121: =Raw_Data!H121
